datek_agar_core/__init__.py
datek_agar_core/game.py
datek_agar_core/network/__init__.py
datek_agar_core/network/client.py
datek_agar_core/network/message.py
datek_agar_core/network/protocol.py
datek_agar_core/network/server.py
datek_agar_core/run_server.py
datek_agar_core/types.py
datek_agar_core/universe.py
datek_agar_core/utils.py
datek_agar_core-0.1.1.dist-info/entry_points.txt
datek_agar_core-0.1.1.dist-info/LICENSE
datek_agar_core-0.1.1.dist-info/WHEEL
datek_agar_core-0.1.1.dist-info/METADATA
datek_agar_core-0.1.1.dist-info/RECORD
